<?xml version="1.0" encoding="UTF-8"?>











<rdf:RDF
  xmlns:rdf="http://www.w3.org/1999/02/22-rdf-syntax-ns#"
  xmlns:rdfs="http://www.w3.org/2000/01/rdf-schema#"
  xmlns:dcterms="http://purl.org/dc/terms/"
  xmlns:dc="http://purl.org/dc/elements/1.1/"
  xmlns="http://purl.org/rss/1.0/">
  <channel rdf:about="http://purl.org/phylo/treebase/phylows/study/TB2:S13814">
    <title>Patterns of diversity and adaptation in Glomeromycota from three prairie grasslands</title>
    <link>http://purl.org/phylo/treebase/phylows/</link>
    <description>Serializations for study/TB2:S13814</description>
    
	
		<prism:section 
			xmlns:prism="http://prismstandard.org/namespaces/1.2/basic/">Study</prism:section>
	
		<tb:identifier.study 
			xmlns:tb="http://purl.org/phylo/treebase/2.0/terms#">13814</tb:identifier.study>
	
		<tb:identifier.study.tb1 
			xmlns:tb="http://purl.org/phylo/treebase/2.0/terms#"></tb:identifier.study.tb1>
	
		<tb:title.study 
			xmlns:tb="http://purl.org/phylo/treebase/2.0/terms#">Patterns of diversity and adaptation in Glomeromycota from three prairie grasslands</tb:title.study>
	
		<dc:date 
			xmlns:dc="http://purl.org/dc/elements/1.1/">2013-01-29</dc:date>
	
		<prism:modificationDate 
			xmlns:prism="http://prismstandard.org/namespaces/1.2/basic/">2013-01-29</prism:modificationDate>
	
		<prism:creationDate 
			xmlns:prism="http://prismstandard.org/namespaces/1.2/basic/">2013-01-13</prism:creationDate>
	
		<dcterms:bibliographicCitation 
			xmlns:dcterms="http://purl.org/dc/terms/">Ji B., Gehring C.A., Wilson G.W., Miller R.M., Flores-rentería L., &amp; Johnson N.C. 2013. Patterns of diversity and adaptation in Glomeromycota from three prairie grasslands. Molecular Ecology, .</dcterms:bibliographicCitation>
	
		<dc:title 
			xmlns:dc="http://purl.org/dc/elements/1.1/">Patterns of diversity and adaptation in Glomeromycota from three prairie grasslands</dc:title>
	
		<dc:creator 
			xmlns:dc="http://purl.org/dc/elements/1.1/">Ji B., Gehring C.A., Wilson G.W., Miller R.M., Flores-rentería L., &amp; Johnson N.C.</dc:creator>
	
		<dc:contributor 
			xmlns:dc="http://purl.org/dc/elements/1.1/">Ji B.</dc:contributor>
	
		<dc:contributor 
			xmlns:dc="http://purl.org/dc/elements/1.1/">Gehring C.A.</dc:contributor>
	
		<dc:contributor 
			xmlns:dc="http://purl.org/dc/elements/1.1/">Wilson G.W.</dc:contributor>
	
		<dc:contributor 
			xmlns:dc="http://purl.org/dc/elements/1.1/">Miller R.M.</dc:contributor>
	
		<dc:contributor 
			xmlns:dc="http://purl.org/dc/elements/1.1/">Flores-rentería L.</dc:contributor>
	
		<dc:contributor 
			xmlns:dc="http://purl.org/dc/elements/1.1/">Johnson N.C.</dc:contributor>
	
		<prism:publicationDate 
			xmlns:prism="http://prismstandard.org/namespaces/1.2/basic/">2013</prism:publicationDate>
	
		<prism:doi 
			xmlns:prism="http://prismstandard.org/namespaces/1.2/basic/"></prism:doi>
	
		<dc:subject 
			xmlns:dc="http://purl.org/dc/elements/1.1/">Arbuscular mycorrhizas</dc:subject>
	
		<dc:subject 
			xmlns:dc="http://purl.org/dc/elements/1.1/">prairies</dc:subject>
	
		<dc:subject 
			xmlns:dc="http://purl.org/dc/elements/1.1/">local adaptation</dc:subject>
	
		<dc:subject 
			xmlns:dc="http://purl.org/dc/elements/1.1/">reciprocal inoculation</dc:subject>
	
		<dc:subject 
			xmlns:dc="http://purl.org/dc/elements/1.1/">Gigaspora</dc:subject>
	
		<prism:publicationName 
			xmlns:prism="http://prismstandard.org/namespaces/1.2/basic/">Molecular Ecology</prism:publicationName>
	
		<dc:publisher 
			xmlns:dc="http://purl.org/dc/elements/1.1/">Molecular Ecology</dc:publisher>
	
		<prism:volume 
			xmlns:prism="http://prismstandard.org/namespaces/1.2/basic/"></prism:volume>
	
		<prism:number 
			xmlns:prism="http://prismstandard.org/namespaces/1.2/basic/"></prism:number>
	    
    
    <items>
      <rdf:Seq>
		<rdf:li rdf:resource="http://purl.org/phylo/treebase/phylows/study/TB2:S13814?format=html"/>
		<rdf:li rdf:resource="http://purl.org/phylo/treebase/phylows/study/TB2:S13814?format=nexml"/>
		<rdf:li rdf:resource="http://purl.org/phylo/treebase/phylows/study/TB2:S13814?format=nexus"/>
		<rdf:li rdf:resource="http://purl.org/phylo/treebase/phylows/study/TB2:S13814?format=rdf"/>
      </rdf:Seq>
    </items>
  </channel>
  
  
  <item rdf:about="http://purl.org/phylo/treebase/phylows/study/TB2:S13814?format=html">
    <title>Web page</title>
    <link>http://purl.org/phylo/treebase/phylows/study/TB2:S13814?format=html</link>
    <description>A human-readable version of the resource</description>
    <dc:format>text/html</dc:format>
    <dc:language>EN-US</dc:language>
  </item>
  
  
  <item rdf:about="http://purl.org/phylo/treebase/phylows/study/TB2:S13814?format=nexml">
    <title>NeXML file</title>
    <link>http://purl.org/phylo/treebase/phylows/study/TB2:S13814?format=nexml</link>
    <description>A NeXML serialization of the resource</description>
    <dc:format>application/xml</dc:format>
  </item>
    
  
  <item rdf:about="http://purl.org/phylo/treebase/phylows/study/TB2:S13814?format=nexus">
    <title>Nexus file</title>
    <link>http://purl.org/phylo/treebase/phylows/study/TB2:S13814?format=nexus</link>
    <description>A Nexus serialization of the resource</description>
    <dc:format>text/plain</dc:format>
  </item>
     
 
</rdf:RDF>