<?xml version="1.0" encoding="UTF-8"?>











<rdf:RDF
  xmlns:rdf="http://www.w3.org/1999/02/22-rdf-syntax-ns#"
  xmlns:rdfs="http://www.w3.org/2000/01/rdf-schema#"
  xmlns:dcterms="http://purl.org/dc/terms/"
  xmlns:dc="http://purl.org/dc/elements/1.1/"
  xmlns="http://purl.org/rss/1.0/">
  <channel rdf:about="http://purl.org/phylo/treebase/phylows/study/TB2:S1710">
    <title>Lactarius in Northern Thailand: 1. Lactarius subgenus Piperites</title>
    <link>http://purl.org/phylo/treebase/phylows/</link>
    <description>Serializations for study/TB2:S1710</description>
    
	
		<prism:section 
			xmlns:prism="http://prismstandard.org/namespaces/1.2/basic/">Study</prism:section>
	
		<tb:identifier.study 
			xmlns:tb="http://purl.org/phylo/treebase/2.0/terms#">1710</tb:identifier.study>
	
		<tb:identifier.study.tb1 
			xmlns:tb="http://purl.org/phylo/treebase/2.0/terms#">S1673</tb:identifier.study.tb1>
	
		<dc:date 
			xmlns:dc="http://purl.org/dc/elements/1.1/">2006-12-09</dc:date>
	
		<prism:modificationDate 
			xmlns:prism="http://prismstandard.org/namespaces/1.2/basic/">2006-12-09</prism:modificationDate>
	
		<prism:creationDate 
			xmlns:prism="http://prismstandard.org/namespaces/1.2/basic/">2006-12-09</prism:creationDate>
	
		<dcterms:bibliographicCitation 
			xmlns:dcterms="http://purl.org/dc/terms/">Le H., Nuytinck J., Verbeken A., Lumyong S., &amp; Desjardin D. 2007. Lactarius in Northern Thailand: 1. Lactarius subgenus Piperites. Fungal Diversity, 24: 111-162.</dcterms:bibliographicCitation>
	
		<dc:title 
			xmlns:dc="http://purl.org/dc/elements/1.1/">Lactarius in Northern Thailand: 1. Lactarius subgenus Piperites</dc:title>
	
		<dc:creator 
			xmlns:dc="http://purl.org/dc/elements/1.1/">Le H., Nuytinck J., Verbeken A., Lumyong S., &amp; Desjardin D.</dc:creator>
	
		<dc:contributor 
			xmlns:dc="http://purl.org/dc/elements/1.1/">Le H.</dc:contributor>
	
		<dc:contributor 
			xmlns:dc="http://purl.org/dc/elements/1.1/">Nuytinck J.</dc:contributor>
	
		<dc:contributor 
			xmlns:dc="http://purl.org/dc/elements/1.1/">Verbeken A.</dc:contributor>
	
		<dc:contributor 
			xmlns:dc="http://purl.org/dc/elements/1.1/">Lumyong S.</dc:contributor>
	
		<dc:contributor 
			xmlns:dc="http://purl.org/dc/elements/1.1/">Desjardin D.</dc:contributor>
	
		<prism:publicationDate 
			xmlns:prism="http://prismstandard.org/namespaces/1.2/basic/">2007</prism:publicationDate>
	
		<prism:startingPage 
			xmlns:prism="http://prismstandard.org/namespaces/1.2/basic/">111</prism:startingPage>
	
		<prism:endingPage 
			xmlns:prism="http://prismstandard.org/namespaces/1.2/basic/">162</prism:endingPage>
	
		<prism:pageRange 
			xmlns:prism="http://prismstandard.org/namespaces/1.2/basic/">111-162</prism:pageRange>
	
		<prism:publicationName 
			xmlns:prism="http://prismstandard.org/namespaces/1.2/basic/">Fungal Diversity</prism:publicationName>
	
		<dc:publisher 
			xmlns:dc="http://purl.org/dc/elements/1.1/">Fungal Diversity</dc:publisher>
	
		<prism:volume 
			xmlns:prism="http://prismstandard.org/namespaces/1.2/basic/">24</prism:volume>
	    
    
    <items>
      <rdf:Seq>
		<rdf:li rdf:resource="http://purl.org/phylo/treebase/phylows/study/TB2:S1710?format=html"/>
		<rdf:li rdf:resource="http://purl.org/phylo/treebase/phylows/study/TB2:S1710?format=nexml"/>
		<rdf:li rdf:resource="http://purl.org/phylo/treebase/phylows/study/TB2:S1710?format=nexus"/>
		<rdf:li rdf:resource="http://purl.org/phylo/treebase/phylows/study/TB2:S1710?format=rdf"/>
      </rdf:Seq>
    </items>
  </channel>
  
  
  <item rdf:about="http://purl.org/phylo/treebase/phylows/study/TB2:S1710?format=html">
    <title>Web page</title>
    <link>http://purl.org/phylo/treebase/phylows/study/TB2:S1710?format=html</link>
    <description>A human-readable version of the resource</description>
    <dc:format>text/html</dc:format>
    <dc:language>EN-US</dc:language>
  </item>
  
  
  <item rdf:about="http://purl.org/phylo/treebase/phylows/study/TB2:S1710?format=nexml">
    <title>NeXML file</title>
    <link>http://purl.org/phylo/treebase/phylows/study/TB2:S1710?format=nexml</link>
    <description>A NeXML serialization of the resource</description>
    <dc:format>application/xml</dc:format>
  </item>
    
  
  <item rdf:about="http://purl.org/phylo/treebase/phylows/study/TB2:S1710?format=nexus">
    <title>Nexus file</title>
    <link>http://purl.org/phylo/treebase/phylows/study/TB2:S1710?format=nexus</link>
    <description>A Nexus serialization of the resource</description>
    <dc:format>text/plain</dc:format>
  </item>
     
 
</rdf:RDF>