<?xml version="1.0" encoding="UTF-8"?>











<rdf:RDF
  xmlns:rdf="http://www.w3.org/1999/02/22-rdf-syntax-ns#"
  xmlns:rdfs="http://www.w3.org/2000/01/rdf-schema#"
  xmlns:dcterms="http://purl.org/dc/terms/"
  xmlns:dc="http://purl.org/dc/elements/1.1/"
  xmlns="http://purl.org/rss/1.0/">
  <channel rdf:about="http://purl.org/phylo/treebase/phylows/study/TB2:S2239">
    <title>Extreme host plant conservatism during at least 20 million years of host plant pursuit by oak gallwasps.</title>
    <link>http://purl.org/phylo/treebase/phylows/</link>
    <description>Serializations for study/TB2:S2239</description>
    
	
		<prism:section 
			xmlns:prism="http://prismstandard.org/namespaces/1.2/basic/">Study</prism:section>
	
		<tb:identifier.study 
			xmlns:tb="http://purl.org/phylo/treebase/2.0/terms#">2239</tb:identifier.study>
	
		<tb:identifier.study.tb1 
			xmlns:tb="http://purl.org/phylo/treebase/2.0/terms#">S2250</tb:identifier.study.tb1>
	
		<dc:date 
			xmlns:dc="http://purl.org/dc/elements/1.1/">2008-12-18</dc:date>
	
		<prism:modificationDate 
			xmlns:prism="http://prismstandard.org/namespaces/1.2/basic/">2008-12-18</prism:modificationDate>
	
		<prism:creationDate 
			xmlns:prism="http://prismstandard.org/namespaces/1.2/basic/">2008-12-18</prism:creationDate>
	
		<dcterms:bibliographicCitation 
			xmlns:dcterms="http://purl.org/dc/terms/">Cook J., Di pierro E., Hernandez-lopez A., Melika G., Nicholls J., Pujade-villar J., Stone G., Pierro E. 2009. Extreme host plant conservatism during at least 20 million years of host plant pursuit by oak gallwasps. Evolution, 63(4): 854-869.</dcterms:bibliographicCitation>
	
		<dc:title 
			xmlns:dc="http://purl.org/dc/elements/1.1/">Extreme host plant conservatism during at least 20 million years of host plant pursuit by oak gallwasps.</dc:title>
	
		<dc:creator 
			xmlns:dc="http://purl.org/dc/elements/1.1/">Cook J., Di pierro E., Hernandez-lopez A., Melika G., Nicholls J., Pujade-villar J., Stone G., Pierro E.</dc:creator>
	
		<dc:contributor 
			xmlns:dc="http://purl.org/dc/elements/1.1/">Cook J.</dc:contributor>
	
		<dc:contributor 
			xmlns:dc="http://purl.org/dc/elements/1.1/">Di pierro E.</dc:contributor>
	
		<dc:contributor 
			xmlns:dc="http://purl.org/dc/elements/1.1/">Hernandez-lopez A.</dc:contributor>
	
		<dc:contributor 
			xmlns:dc="http://purl.org/dc/elements/1.1/">Melika G.</dc:contributor>
	
		<dc:contributor 
			xmlns:dc="http://purl.org/dc/elements/1.1/">Nicholls J.</dc:contributor>
	
		<dc:contributor 
			xmlns:dc="http://purl.org/dc/elements/1.1/">Pujade-villar J.</dc:contributor>
	
		<dc:contributor 
			xmlns:dc="http://purl.org/dc/elements/1.1/">Stone G.</dc:contributor>
	
		<dc:contributor 
			xmlns:dc="http://purl.org/dc/elements/1.1/">Pierro E.</dc:contributor>
	
		<prism:publicationDate 
			xmlns:prism="http://prismstandard.org/namespaces/1.2/basic/">2009</prism:publicationDate>
	
		<prism:doi 
			xmlns:prism="http://prismstandard.org/namespaces/1.2/basic/">10.1111/j.1558-5646.2008.00604.x</prism:doi>
	
		<prism:startingPage 
			xmlns:prism="http://prismstandard.org/namespaces/1.2/basic/">854</prism:startingPage>
	
		<prism:endingPage 
			xmlns:prism="http://prismstandard.org/namespaces/1.2/basic/">869</prism:endingPage>
	
		<prism:pageRange 
			xmlns:prism="http://prismstandard.org/namespaces/1.2/basic/">854-869</prism:pageRange>
	
		<dc:subject 
			xmlns:dc="http://purl.org/dc/elements/1.1/"></dc:subject>
	
		<prism:publicationName 
			xmlns:prism="http://prismstandard.org/namespaces/1.2/basic/">Evolution</prism:publicationName>
	
		<dc:publisher 
			xmlns:dc="http://purl.org/dc/elements/1.1/">Evolution</dc:publisher>
	
		<prism:volume 
			xmlns:prism="http://prismstandard.org/namespaces/1.2/basic/">63</prism:volume>
	
		<prism:number 
			xmlns:prism="http://prismstandard.org/namespaces/1.2/basic/">4</prism:number>
	    
    
    <items>
      <rdf:Seq>
		<rdf:li rdf:resource="http://purl.org/phylo/treebase/phylows/study/TB2:S2239?format=html"/>
		<rdf:li rdf:resource="http://purl.org/phylo/treebase/phylows/study/TB2:S2239?format=nexml"/>
		<rdf:li rdf:resource="http://purl.org/phylo/treebase/phylows/study/TB2:S2239?format=nexus"/>
		<rdf:li rdf:resource="http://purl.org/phylo/treebase/phylows/study/TB2:S2239?format=rdf"/>
      </rdf:Seq>
    </items>
  </channel>
  
  
  <item rdf:about="http://purl.org/phylo/treebase/phylows/study/TB2:S2239?format=html">
    <title>Web page</title>
    <link>http://purl.org/phylo/treebase/phylows/study/TB2:S2239?format=html</link>
    <description>A human-readable version of the resource</description>
    <dc:format>text/html</dc:format>
    <dc:language>EN-US</dc:language>
  </item>
  
  
  <item rdf:about="http://purl.org/phylo/treebase/phylows/study/TB2:S2239?format=nexml">
    <title>NeXML file</title>
    <link>http://purl.org/phylo/treebase/phylows/study/TB2:S2239?format=nexml</link>
    <description>A NeXML serialization of the resource</description>
    <dc:format>application/xml</dc:format>
  </item>
    
  
  <item rdf:about="http://purl.org/phylo/treebase/phylows/study/TB2:S2239?format=nexus">
    <title>Nexus file</title>
    <link>http://purl.org/phylo/treebase/phylows/study/TB2:S2239?format=nexus</link>
    <description>A Nexus serialization of the resource</description>
    <dc:format>text/plain</dc:format>
  </item>
     
 
</rdf:RDF>